[
  {
    "name": "1800s",
    "range": "1800-1809"
  },
  {
    "name": "1810s",
    "range": "1810-1819"
  },
  {
    "name": "1820s",
    "range": "1820-1829"
  },
  {
    "name": "1830s",
    "range": "1830-1839"
  },
  {
    "name": "1840s",
    "range": "1840-1849"
  },
  {
    "name": "1850s",
    "range": "1850-1859"
  },
  {
    "name": "1860s",
    "range": "1860-1869"
  },
  {
    "name": "1870s",
    "range": "1870-1879"
  },
  {
    "name": "1880s",
    "range": "1880-1889"
  },
  {
    "name": "1890s",
    "range": "1890-1899"
  },
  {
    "name": "1900s",
    "range": "1900-1909"
  },
  {
    "name": "1910s",
    "range": "1910-1919"
  },
  {
    "name": "1920s",
    "range": "1920-1929"
  },
  {
    "name": "1930s",
    "range": "1930-1939"
  },
  {
    "name": "1940s",
    "range": "1940-1949"
  },
  {
    "name": "1950s",
    "range": "1950-1959"
  },
  {
    "name": "1960s",
    "range": "1960-1969"
  },
  {
    "name": "1970s",
    "range": "1970-1979"
  },
  {
    "name": "1980s",
    "range": "1980-1989"
  },
  {
    "name": "1990s",
    "range": "1990-1999"
  },
  {
    "name": "2000s",
    "range": "2000-2009"
  },
  {
    "name": "2010s",
    "range": "2010-2019"
  },
  {
    "name": "2020s",
    "range": "2020-2029"
   }
]